{
    "team": [
        {
            "name": "ウーゴ ロリス",
            "number": "1",
            "body": "188cm/82k",
            "team": "トッテナム ホットスパー"
        }, {
            "name": "スティーブ マンダンダ",
            "number": "16",
            "body": "187cm/88k",
            "team": "マルセイユ"
        }, {
            "name": "アルフォンス アレオラ",
            "number": "23",
            "body": "195cm/95k",
            "team": "パリ サンジェルマン"
        }, {
            "name": "バンジャマン パバール",
            "number": "2",
            "body": "186cm/76k",
            "team": "VfBシュツットガルト"
        }, {
            "name": "プレスネル キンペンベ",
            "number": "3",
            "body": "182cm/78k",
            "team": "パリ サンジェルマン"
        }, {
            "name": "ラファエル ヴァラン",
            "number": "4",
            "body": "191cm/79k",
            "team": "レアル マドリー"
        }, {
            "name": "サミュエル ウムティティ",
            "number": "5",
            "body": "183cm/84k",
            "team": "バルセロナ"
        }, {
            "name": "アディル ラミ",
            "number": "17",
            "body": "190cm/90k",
            "team": "マルセイユ"
        }, {
            "name": "ジブリル シディベ",
            "number": "19",
            "body": "184cm/81k",
            "team": "モナコ"
        }, {
            "name": "リュカ エルナンデス",
            "number": "21",
            "body": "183cm/76k",
            "team": "アトレティコ マドリー"
        }, {
            "name": "バンジャマン メンディ",
            "number": "22",
            "body": "183cm/84k",
            "team": "マンチェスター シティ"
        }, {
            "name": "ポール ポグバ",
            "number": "6",
            "body": "191cm/86k",
            "team": "マンチェスター ユナイテッド"
        }, {
            "name": "コランタン トリソ",
            "number": "12",
            "body": "180cm/82k",
            "team": "バイエルン ミュンヘン"
        }, {
            "name": "エンゴロ カンテ",
            "number": "13",
            "body": "168cm/70k",
            "team": "チェルシー"
        }, {
            "name": "ブレーズ マテュイディ",
            "number": "14",
            "body": "180cm/74k",
            "team": "ユベントス"
        }, {
            "name": "スティーブン エンゾンジ",
            "number": "15",
            "body": "197cm/87k",
            "team": "セビージャFC"
        }, {
            "name": "アントワーヌ グリーズマン",
            "number": "7",
            "body": "174cm/72k",
            "team": "アトレティコ マドリー"
        }, {
            "name": "トマ レマル",
            "number": "8",
            "body": "172cm/65k",
            "team": "モナコ"
        }, {
            "name": "オリビエ ジルー",
            "number": "9",
            "body": "193cm/91k",
            "team": "チェルシー"
        }, {
            "name": "キリアン エムバペ",
            "number": "10",
            "body": "178cm/78k",
            "team": "パリ サンジェルマン"
        }, {
            "name": "ウスマン デンベレ",
            "number": "11",
            "body": "178cm/70k",
            "team": "バルセロナ"
        }, {
            "name": "ナビル フェキル",
            "number": "18",
            "body": "173cm/76k",
            "team": "オリンピック リヨン"
        }, {
            "name": "フロリアン トバン",
            "number": "20",
            "body": "180cm/76k",
            "team": "マルセイユ"
        }

    ]
}